obsidian_progress_report/__init__.py
obsidian_progress_report/__main__.py
obsidian_progress_report/report.py
obsidian_progress_report-0.3.0.dist-info/METADATA
obsidian_progress_report-0.3.0.dist-info/WHEEL
obsidian_progress_report-0.3.0.dist-info/entry_points.txt
obsidian_progress_report-0.3.0.dist-info/top_level.txt
obsidian_progress_report-0.3.0.dist-info/RECORD
