Metadata-Version: 2.1
Name: obsidian-progress-report
Version: 0.3.0
Summary: A simple command line app for generating progress report for contributions in the Obsidian vault
Home-page: https://github.com/aviskase/obsidian-progress-report
Author: Yuliya Bagriy
Author-email: aviskase@gmail.com
License: Unlicense
Download-URL: https://github.com/aviskase/obsidian-progress-report/archive/0.3.0.tar.gz
Platform: UNKNOWN
Classifier: License :: Public Domain
Classifier: Programming Language :: Python :: 3
Classifier: Programming Language :: Python :: 3.8
Requires-Python: >=3.8
Requires-Dist: frontmatter (~=3.0)
